{"artists": [{"external_urls": {"spotify": "https://open.spotify.com/artist/13y7CgLHjMVRMDqxdx0Xdo"}, "href": "https://api.spotify.com/v1/artists/13y7CgLHjMVRMDqxdx0Xdo", "id": "13y7CgLHjMVRMDqxdx0Xdo", "name": "Gucci Mane", "type": "artist", "uri": "spotify:artist:13y7CgLHjMVRMDqxdx0Xdo"}, {"external_urls": {"spotify": "https://open.spotify.com/artist/6hZYWGioZNvVFoEwoufVJw"}, "href": "https://api.spotify.com/v1/artists/6hZYWGioZNvVFoEwoufVJw", "id": "6hZYWGioZNvVFoEwoufVJw", "name": "Figg Panamera", "type": "artist", "uri": "spotify:artist:6hZYWGioZNvVFoEwoufVJw"}, {"external_urls": {"spotify": "https://open.spotify.com/artist/1gPhS1zisyXr5dHTYZyiMe"}, "href": "https://api.spotify.com/v1/artists/1gPhS1zisyXr5dHTYZyiMe", "id": "1gPhS1zisyXr5dHTYZyiMe", "name": "Kevin Gates", "type": "artist", "uri": "spotify:artist:1gPhS1zisyXr5dHTYZyiMe"}], "available_markets": ["IN"], "disc_number": 1, "duration_ms": 143360, "explicit": true, "external_urls": {"spotify": "https://open.spotify.com/track/00S84X7717TDeGN2MwyfNx"}, "href": "https://api.spotify.com/v1/tracks/00S84X7717TDeGN2MwyfNx", "id": "00S84X7717TDeGN2MwyfNx", "is_local": false, "name": "Bitch I'm Okay (feat. Kevin Gates)", "preview_url": "https://p.scdn.co/mp3-preview/c0b6ace8b10db73a2c58dc7deabb85201511f64a?cid=3babc6a11c1148728bac51aef1937f54", "track_number": 2, "type": "track", "uri": "spotify:track:00S84X7717TDeGN2MwyfNx"}