{"artists": [{"external_urls": {"spotify": "https://open.spotify.com/artist/2Jwr7hGoSNK3S3QBxh3T0z"}, "href": "https://api.spotify.com/v1/artists/2Jwr7hGoSNK3S3QBxh3T0z", "id": "2Jwr7hGoSNK3S3QBxh3T0z", "name": "Freeway", "type": "artist", "uri": "spotify:artist:2Jwr7hGoSNK3S3QBxh3T0z"}, {"external_urls": {"spotify": "https://open.spotify.com/artist/1Z3HvW1V35gdsbhY20SMoU"}, "href": "https://api.spotify.com/v1/artists/1Z3HvW1V35gdsbhY20SMoU", "id": "1Z3HvW1V35gdsbhY20SMoU", "name": "The Jacka", "type": "artist", "uri": "spotify:artist:1Z3HvW1V35gdsbhY20SMoU"}, {"external_urls": {"spotify": "https://open.spotify.com/artist/7AhHVlLPrLqmGJ4MOzs5Iw"}, "href": "https://api.spotify.com/v1/artists/7AhHVlLPrLqmGJ4MOzs5Iw", "id": "7AhHVlLPrLqmGJ4MOzs5Iw", "name": "Fed-X", "type": "artist", "uri": "spotify:artist:7AhHVlLPrLqmGJ4MOzs5Iw"}, {"external_urls": {"spotify": "https://open.spotify.com/artist/1ncXAeWJfq6pZpD7fu9ExD"}, "href": "https://api.spotify.com/v1/artists/1ncXAeWJfq6pZpD7fu9ExD", "id": "1ncXAeWJfq6pZpD7fu9ExD", "name": "DJ Child", "type": "artist", "uri": "spotify:artist:1ncXAeWJfq6pZpD7fu9ExD"}], "available_markets": ["AD", "AE", "AG", "AL", "AM", "AO", "AR", "AT", "AU", "AZ", "BA", "BB", "BD", "BE", "BF", "BG", "BH", "BI", "BJ", "BN", "BO", "BR", "BS", "BT", "BW", "BY", "BZ", "CA", "CD", "CG", "CH", "CI", "CL", "CM", "CO", "CR", "CV", "CY", "CZ", "DE", "DJ", "DK", "DM", "DO", "DZ", "EC", "EE", "EG", "ES", "FI", "FJ", "FM", "FR", "GA", "GB", "GD", "GE", "GH", "GM", "GN", "GQ", "GR", "GT", "GW", "GY", "HK", "HN", "HR", "HT", "HU", "ID", "IE", "IL", "IN", "IQ", "IS", "IT", "JM", "JO", "JP", "KE", "KG", "KH", "KI", "KM", "KN", "KR", "KW", "KZ", "LA", "LB", "LC", "LI", "LK", "LR", "LS", "LT", "LU", "LV", "LY", "MA", "MC", "MD", "ME", "MG", "MH", "MK", "ML", "MN", "MO", "MR", "MT", "MU", "MV", "MW", "MX", "MY", "MZ", "NA", "NE", "NG", "NI", "NL", "NO", "NP", "NR", "NZ", "OM", "PA", "PE", "PG", "PH", "PK", "PL", "PS", "PT", "PW", "PY", "QA", "RO", "RS", "RW", "SA", "SB", "SC", "SE", "SG", "SI", "SK", "SL", "SM", "SN", "SR", "ST", "SV", "SZ", "TD", "TG", "TH", "TJ", "TL", "TN", "TO", "TR", "TT", "TV", "TW", "TZ", "UA", "UG", "US", "UY", "UZ", "VC", "VE", "VN", "VU", "WS", "XK", "ZA", "ZM", "ZW"], "disc_number": 1, "duration_ms": 138266, "explicit": true, "external_urls": {"spotify": "https://open.spotify.com/track/5w7iloPaOSPpAXqLJSNvtC"}, "href": "https://api.spotify.com/v1/tracks/5w7iloPaOSPpAXqLJSNvtC", "id": "5w7iloPaOSPpAXqLJSNvtC", "is_local": false, "name": "So Many Animals (Remix)", "preview_url": "https://p.scdn.co/mp3-preview/343daf1b8f0c811643bf90bd77c4a9a0718b2902?cid=3babc6a11c1148728bac51aef1937f54", "track_number": 17, "type": "track", "uri": "spotify:track:5w7iloPaOSPpAXqLJSNvtC", "release_date": "2014-11-18"}