{"artists": [{"external_urls": {"spotify": "https://open.spotify.com/artist/13y7CgLHjMVRMDqxdx0Xdo"}, "href": "https://api.spotify.com/v1/artists/13y7CgLHjMVRMDqxdx0Xdo", "id": "13y7CgLHjMVRMDqxdx0Xdo", "name": "Gucci Mane", "type": "artist", "uri": "spotify:artist:13y7CgLHjMVRMDqxdx0Xdo"}, {"external_urls": {"spotify": "https://open.spotify.com/artist/35sCXuy5gN6Or69rZ9vqBs"}, "href": "https://api.spotify.com/v1/artists/35sCXuy5gN6Or69rZ9vqBs", "id": "35sCXuy5gN6Or69rZ9vqBs", "name": "Birdman", "type": "artist", "uri": "spotify:artist:35sCXuy5gN6Or69rZ9vqBs"}], "available_markets": ["IN"], "disc_number": 1, "duration_ms": 265586, "explicit": true, "external_urls": {"spotify": "https://open.spotify.com/track/6Oyju0cczIbpc6haxUs7XG"}, "href": "https://api.spotify.com/v1/tracks/6Oyju0cczIbpc6haxUs7XG", "id": "6Oyju0cczIbpc6haxUs7XG", "is_local": false, "name": "Mouth Full of Gold (feat. Birdman)", "preview_url": "https://p.scdn.co/mp3-preview/d9a3154c054565f87c117af527c1a4366e491425?cid=3babc6a11c1148728bac51aef1937f54", "track_number": 4, "type": "track", "uri": "spotify:track:6Oyju0cczIbpc6haxUs7XG", "release_date": "2015-12-11"}