{"artists": [{"external_urls": {"spotify": "https://open.spotify.com/artist/3HQyFCFFfJO3KKBlUfZsyW"}, "href": "https://api.spotify.com/v1/artists/3HQyFCFFfJO3KKBlUfZsyW", "id": "3HQyFCFFfJO3KKBlUfZsyW", "name": "Randy Newman", "type": "artist", "uri": "spotify:artist:3HQyFCFFfJO3KKBlUfZsyW"}], "available_markets": ["AD", "AL", "AT", "BA", "BE", "BG", "BY", "CH", "CY", "CZ", "DK", "EE", "ES", "FI", "FR", "GB", "GR", "HR", "HU", "IE", "IS", "IT", "LI", "LT", "LU", "LV", "MC", "MD", "ME", "MK", "MT", "NL", "NO", "PL", "PT", "RO", "RS", "SE", "SI", "SK", "SM", "UA", "XK"], "disc_number": 1, "duration_ms": 172173, "explicit": false, "external_urls": {"spotify": "https://open.spotify.com/track/27upmOzUvgR6LspVpNZ7Ne"}, "href": "https://api.spotify.com/v1/tracks/27upmOzUvgR6LspVpNZ7Ne", "id": "27upmOzUvgR6LspVpNZ7Ne", "is_local": false, "name": "Kingfish", "preview_url": "https://p.scdn.co/mp3-preview/cc5ba8047633b18b0ced5fd9add2057c87b982f6?cid=3babc6a11c1148728bac51aef1937f54", "track_number": 15, "type": "track", "uri": "spotify:track:27upmOzUvgR6LspVpNZ7Ne"}