{"artists": [{"external_urls": {"spotify": "https://open.spotify.com/artist/3crnzLy8R4lVwaigKEOz7V"}, "href": "https://api.spotify.com/v1/artists/3crnzLy8R4lVwaigKEOz7V", "id": "3crnzLy8R4lVwaigKEOz7V", "name": "E-40", "type": "artist", "uri": "spotify:artist:3crnzLy8R4lVwaigKEOz7V"}, {"external_urls": {"spotify": "https://open.spotify.com/artist/1ph49vsN9CWxsCJgdtn2YP"}, "href": "https://api.spotify.com/v1/artists/1ph49vsN9CWxsCJgdtn2YP", "id": "1ph49vsN9CWxsCJgdtn2YP", "name": "Dem Hoodstarz", "type": "artist", "uri": "spotify:artist:1ph49vsN9CWxsCJgdtn2YP"}, {"external_urls": {"spotify": "https://open.spotify.com/artist/55TH3aMMK1u2VsR8DPGC6D"}, "href": "https://api.spotify.com/v1/artists/55TH3aMMK1u2VsR8DPGC6D", "id": "55TH3aMMK1u2VsR8DPGC6D", "name": "Mistah F.A.B.", "type": "artist", "uri": "spotify:artist:55TH3aMMK1u2VsR8DPGC6D"}], "available_markets": ["US"], "disc_number": 1, "duration_ms": 213440, "explicit": true, "external_urls": {"spotify": "https://open.spotify.com/track/6IECyJlLnjKWqVhH457k0U"}, "href": "https://api.spotify.com/v1/tracks/6IECyJlLnjKWqVhH457k0U", "id": "6IECyJlLnjKWqVhH457k0U", "is_local": false, "name": "Outta Control", "preview_url": null, "track_number": 17, "type": "track", "uri": "spotify:track:6IECyJlLnjKWqVhH457k0U"}