{"artists": [{"external_urls": {"spotify": "https://open.spotify.com/artist/6ohaQzKaXrobAL8paLSaxq"}, "href": "https://api.spotify.com/v1/artists/6ohaQzKaXrobAL8paLSaxq", "id": "6ohaQzKaXrobAL8paLSaxq", "name": "Salim\u2013Sulaiman", "type": "artist", "uri": "spotify:artist:6ohaQzKaXrobAL8paLSaxq"}, {"external_urls": {"spotify": "https://open.spotify.com/artist/4oVMLzAqW6qhRpZWt8fNw4"}, "href": "https://api.spotify.com/v1/artists/4oVMLzAqW6qhRpZWt8fNw4", "id": "4oVMLzAqW6qhRpZWt8fNw4", "name": "Kailash Kher", "type": "artist", "uri": "spotify:artist:4oVMLzAqW6qhRpZWt8fNw4"}, {"external_urls": {"spotify": "https://open.spotify.com/artist/77O3f27AfiufcqVGEW13NQ"}, "href": "https://api.spotify.com/v1/artists/77O3f27AfiufcqVGEW13NQ", "id": "77O3f27AfiufcqVGEW13NQ", "name": "Munawar Masoom", "type": "artist", "uri": "spotify:artist:77O3f27AfiufcqVGEW13NQ"}], "available_markets": ["BD", "BT", "IN", "LK", "MV", "NP", "PK"], "disc_number": 1, "duration_ms": 585693, "explicit": false, "external_urls": {"spotify": "https://open.spotify.com/track/6p2SNQ94rBUKIALWM2IoFr"}, "href": "https://api.spotify.com/v1/tracks/6p2SNQ94rBUKIALWM2IoFr", "id": "6p2SNQ94rBUKIALWM2IoFr", "is_local": false, "name": "Bismillah", "preview_url": "https://p.scdn.co/mp3-preview/827656e341fa97917f9b2924baed1f96b671c591?cid=3babc6a11c1148728bac51aef1937f54", "track_number": 1, "type": "track", "uri": "spotify:track:6p2SNQ94rBUKIALWM2IoFr", "release_date": "2013-09-07"}