{"artists": [{"external_urls": {"spotify": "https://open.spotify.com/artist/16kOCiqZ1auY4sokSeZuKf"}, "href": "https://api.spotify.com/v1/artists/16kOCiqZ1auY4sokSeZuKf", "id": "16kOCiqZ1auY4sokSeZuKf", "name": "Los Bukis", "type": "artist", "uri": "spotify:artist:16kOCiqZ1auY4sokSeZuKf"}], "available_markets": ["AE", "AG", "AR", "AT", "BA", "BB", "BH", "BN", "BO", "BS", "CL", "CO", "CR", "DE", "DM", "DO", "EC", "EG", "ES", "FJ", "FR", "GD", "GT", "GY", "HK", "HN", "HR", "HT", "HU", "ID", "IL", "IS", "JM", "JO", "KN", "KR", "LB", "LC", "LK", "ME", "MK", "MO", "MX", "MY", "NI", "NL", "NO", "OM", "PA", "PE", "PH", "PK", "PT", "PY", "QA", "RS", "SA", "SI", "SR", "SV", "TN", "TR", "TT", "TW", "US", "VC", "VE", "XK", "ZA"], "disc_number": 1, "duration_ms": 235560, "explicit": false, "external_urls": {"spotify": "https://open.spotify.com/track/4YRTgE2C2tSx30urg0jUKl"}, "href": "https://api.spotify.com/v1/tracks/4YRTgE2C2tSx30urg0jUKl", "id": "4YRTgE2C2tSx30urg0jUKl", "is_local": false, "name": "Adios Querida Esposa", "preview_url": null, "track_number": 9, "type": "track", "uri": "spotify:track:4YRTgE2C2tSx30urg0jUKl", "release_date": "2001-01-01"}