{"artists": [{"external_urls": {"spotify": "https://open.spotify.com/artist/13y7CgLHjMVRMDqxdx0Xdo"}, "href": "https://api.spotify.com/v1/artists/13y7CgLHjMVRMDqxdx0Xdo", "id": "13y7CgLHjMVRMDqxdx0Xdo", "name": "Gucci Mane", "type": "artist", "uri": "spotify:artist:13y7CgLHjMVRMDqxdx0Xdo"}, {"external_urls": {"spotify": "https://open.spotify.com/artist/0t5qZrvVCo9YIUT87SQrTn"}, "href": "https://api.spotify.com/v1/artists/0t5qZrvVCo9YIUT87SQrTn", "id": "0t5qZrvVCo9YIUT87SQrTn", "name": "OJ Da Juiceman", "type": "artist", "uri": "spotify:artist:0t5qZrvVCo9YIUT87SQrTn"}], "available_markets": ["IN"], "disc_number": 1, "duration_ms": 177160, "explicit": true, "external_urls": {"spotify": "https://open.spotify.com/track/6L55R0qRmopw9wziRIohkA"}, "href": "https://api.spotify.com/v1/tracks/6L55R0qRmopw9wziRIohkA", "id": "6L55R0qRmopw9wziRIohkA", "is_local": false, "name": "Party Started (feat. OJ da Juiceman)", "preview_url": "https://p.scdn.co/mp3-preview/79e4c90dbe2066138333120e4423ee7d1b368d85?cid=3babc6a11c1148728bac51aef1937f54", "track_number": 9, "type": "track", "uri": "spotify:track:6L55R0qRmopw9wziRIohkA", "release_date": "2015-12-11"}