{"artists": [{"external_urls": {"spotify": "https://open.spotify.com/artist/2iojnBLj0qIMiKPvVhLnsH"}, "href": "https://api.spotify.com/v1/artists/2iojnBLj0qIMiKPvVhLnsH", "id": "2iojnBLj0qIMiKPvVhLnsH", "name": "Trey Songz", "type": "artist", "uri": "spotify:artist:2iojnBLj0qIMiKPvVhLnsH"}], "available_markets": ["CA", "US"], "disc_number": 1, "duration_ms": 178546, "explicit": false, "external_urls": {"spotify": "https://open.spotify.com/track/41tKHNKzcp94XzctAa2YAU"}, "href": "https://api.spotify.com/v1/tracks/41tKHNKzcp94XzctAa2YAU", "id": "41tKHNKzcp94XzctAa2YAU", "is_local": false, "name": "Does He Do It", "preview_url": "https://p.scdn.co/mp3-preview/92df847d84c40ddd81d792734d70af6e7d5ecf5f?cid=3babc6a11c1148728bac51aef1937f54", "track_number": 6, "type": "track", "uri": "spotify:track:41tKHNKzcp94XzctAa2YAU", "release_date": "2009-08-31"}