{"artists": [{"external_urls": {"spotify": "https://open.spotify.com/artist/4AA474G2hRfrHyGrfyDseO"}, "href": "https://api.spotify.com/v1/artists/4AA474G2hRfrHyGrfyDseO", "id": "4AA474G2hRfrHyGrfyDseO", "name": "Mozzy", "type": "artist", "uri": "spotify:artist:4AA474G2hRfrHyGrfyDseO"}, {"external_urls": {"spotify": "https://open.spotify.com/artist/3E6fHPDfPcfAEbXP9L1SZN"}, "href": "https://api.spotify.com/v1/artists/3E6fHPDfPcfAEbXP9L1SZN", "id": "3E6fHPDfPcfAEbXP9L1SZN", "name": "Cellyru", "type": "artist", "uri": "spotify:artist:3E6fHPDfPcfAEbXP9L1SZN"}, {"external_urls": {"spotify": "https://open.spotify.com/artist/7fJpPNIfiCquB6WS54obHl"}, "href": "https://api.spotify.com/v1/artists/7fJpPNIfiCquB6WS54obHl", "id": "7fJpPNIfiCquB6WS54obHl", "name": "Kelz", "type": "artist", "uri": "spotify:artist:7fJpPNIfiCquB6WS54obHl"}, {"external_urls": {"spotify": "https://open.spotify.com/artist/01L44yiVRL26vEIfcXYfXR"}, "href": "https://api.spotify.com/v1/artists/01L44yiVRL26vEIfcXYfXR", "id": "01L44yiVRL26vEIfcXYfXR", "name": "Ty Illa", "type": "artist", "uri": "spotify:artist:01L44yiVRL26vEIfcXYfXR"}], "available_markets": ["AD", "AE", "AG", "AL", "AM", "AO", "AR", "AT", "AU", "AZ", "BA", "BB", "BD", "BE", "BF", "BG", "BH", "BI", "BJ", "BN", "BO", "BR", "BS", "BT", "BW", "BY", "BZ", "CA", "CD", "CG", "CH", "CI", "CL", "CM", "CO", "CR", "CV", "CW", "CY", "CZ", "DE", "DJ", "DK", "DM", "DO", "DZ", "EC", "EE", "EG", "ES", "FI", "FJ", "FM", "FR", "GA", "GB", "GD", "GE", "GH", "GM", "GN", "GQ", "GR", "GT", "GW", "GY", "HK", "HN", "HR", "HT", "HU", "ID", "IE", "IL", "IN", "IQ", "IS", "IT", "JM", "JO", "JP", "KE", "KG", "KH", "KI", "KM", "KN", "KR", "KW", "KZ", "LA", "LB", "LC", "LI", "LK", "LR", "LS", "LT", "LU", "LV", "LY", "MA", "MC", "MD", "ME", "MG", "MH", "MK", "ML", "MN", "MO", "MR", "MT", "MU", "MV", "MW", "MX", "MY", "MZ", "NA", "NE", "NG", "NI", "NL", "NO", "NP", "NR", "NZ", "OM", "PA", "PE", "PG", "PH", "PK", "PL", "PS", "PT", "PW", "PY", "QA", "RO", "RS", "RW", "SA", "SB", "SC", "SE", "SG", "SI", "SK", "SL", "SM", "SN", "SR", "ST", "SV", "SZ", "TD", "TG", "TH", "TJ", "TL", "TN", "TO", "TR", "TT", "TV", "TW", "TZ", "UA", "UG", "US", "UY", "UZ", "VC", "VE", "VN", "VU", "WS", "XK", "ZA", "ZM", "ZW"], "disc_number": 1, "duration_ms": 305738, "explicit": true, "external_urls": {"spotify": "https://open.spotify.com/track/1R20KRKBcu9es8LQk2rXCn"}, "href": "https://api.spotify.com/v1/tracks/1R20KRKBcu9es8LQk2rXCn", "id": "1R20KRKBcu9es8LQk2rXCn", "is_local": false, "name": "Swear 2 God (feat. Cellyru, Kelz & Ty Illa)", "preview_url": "https://p.scdn.co/mp3-preview/475c7c63f0f189dd33eee32de8d12c15da8f3120?cid=3babc6a11c1148728bac51aef1937f54", "track_number": 10, "type": "track", "uri": "spotify:track:1R20KRKBcu9es8LQk2rXCn", "release_date": "2014-04-19"}