{"artists": [{"external_urls": {"spotify": "https://open.spotify.com/artist/6GMYJwaziB4ekv1Y6wCDWS"}, "href": "https://api.spotify.com/v1/artists/6GMYJwaziB4ekv1Y6wCDWS", "id": "6GMYJwaziB4ekv1Y6wCDWS", "name": "Soulja Boy", "type": "artist", "uri": "spotify:artist:6GMYJwaziB4ekv1Y6wCDWS"}], "available_markets": ["DE"], "disc_number": 1, "duration_ms": 232133, "explicit": false, "external_urls": {"spotify": "https://open.spotify.com/track/5T9I7kUX7tqoEPMyhkGrgR"}, "href": "https://api.spotify.com/v1/tracks/5T9I7kUX7tqoEPMyhkGrgR", "id": "5T9I7kUX7tqoEPMyhkGrgR", "is_local": false, "name": "Hey You There", "preview_url": null, "track_number": 9, "type": "track", "uri": "spotify:track:5T9I7kUX7tqoEPMyhkGrgR", "release_date": "2008-01-01"}