{"artists": [{"external_urls": {"spotify": "https://open.spotify.com/artist/13y7CgLHjMVRMDqxdx0Xdo"}, "href": "https://api.spotify.com/v1/artists/13y7CgLHjMVRMDqxdx0Xdo", "id": "13y7CgLHjMVRMDqxdx0Xdo", "name": "Gucci Mane", "type": "artist", "uri": "spotify:artist:13y7CgLHjMVRMDqxdx0Xdo"}], "available_markets": ["IN"], "disc_number": 1, "duration_ms": 257018, "explicit": true, "external_urls": {"spotify": "https://open.spotify.com/track/34pefhDdNK8iUvRXYJpzh2"}, "href": "https://api.spotify.com/v1/tracks/34pefhDdNK8iUvRXYJpzh2", "id": "34pefhDdNK8iUvRXYJpzh2", "is_local": false, "name": "Ice on Me", "preview_url": "https://p.scdn.co/mp3-preview/9b3302a3514899ea1f9cac47ede71c9b431ee36e?cid=3babc6a11c1148728bac51aef1937f54", "track_number": 1, "type": "track", "uri": "spotify:track:34pefhDdNK8iUvRXYJpzh2"}