{"artists": [{"external_urls": {"spotify": "https://open.spotify.com/artist/13y7CgLHjMVRMDqxdx0Xdo"}, "href": "https://api.spotify.com/v1/artists/13y7CgLHjMVRMDqxdx0Xdo", "id": "13y7CgLHjMVRMDqxdx0Xdo", "name": "Gucci Mane", "type": "artist", "uri": "spotify:artist:13y7CgLHjMVRMDqxdx0Xdo"}], "available_markets": ["IN"], "disc_number": 1, "duration_ms": 176117, "explicit": true, "external_urls": {"spotify": "https://open.spotify.com/track/5EmnpwIdgMqO6sg5brgRw7"}, "href": "https://api.spotify.com/v1/tracks/5EmnpwIdgMqO6sg5brgRw7", "id": "5EmnpwIdgMqO6sg5brgRw7", "is_local": false, "name": "One Minute", "preview_url": "https://p.scdn.co/mp3-preview/d877fd70cb0f8ededd4f41f17660462f92b5bb3d?cid=3babc6a11c1148728bac51aef1937f54", "track_number": 1, "type": "track", "uri": "spotify:track:5EmnpwIdgMqO6sg5brgRw7"}