{"artists": [{"external_urls": {"spotify": "https://open.spotify.com/artist/4akybxRTGHJZ1DXjLhJ1qu"}, "href": "https://api.spotify.com/v1/artists/4akybxRTGHJZ1DXjLhJ1qu", "id": "4akybxRTGHJZ1DXjLhJ1qu", "name": "Kirk Franklin", "type": "artist", "uri": "spotify:artist:4akybxRTGHJZ1DXjLhJ1qu"}], "available_markets": ["AG", "AO", "AR", "BB", "BD", "BF", "BI", "BJ", "BN", "BO", "BR", "BS", "BT", "BW", "BZ", "CD", "CG", "CI", "CL", "CM", "CO", "CR", "CV", "CW", "DJ", "DM", "DO", "EC", "FM", "GA", "GD", "GH", "GM", "GN", "GQ", "GT", "GW", "GY", "HK", "HN", "HT", "ID", "IN", "JM", "KE", "KH", "KM", "KN", "KR", "LA", "LC", "LK", "LR", "LS", "MG", "ML", "MO", "MR", "MU", "MV", "MW", "MX", "MY", "MZ", "NA", "NE", "NG", "NI", "NP", "PA", "PE", "PH", "PK", "PY", "RW", "SC", "SG", "SL", "SN", "SR", "ST", "SV", "SZ", "TD", "TG", "TH", "TL", "TT", "TW", "TZ", "UG", "US", "UY", "VC", "VE", "VN", "ZA", "ZM", "ZW"], "disc_number": 1, "duration_ms": 211026, "explicit": false, "external_urls": {"spotify": "https://open.spotify.com/track/6UweTkm7cVKfWIw6Sn1iU7"}, "href": "https://api.spotify.com/v1/tracks/6UweTkm7cVKfWIw6Sn1iU7", "id": "6UweTkm7cVKfWIw6Sn1iU7", "is_local": false, "name": "Call On The Lord", "preview_url": "https://p.scdn.co/mp3-preview/8eed9f8f133e42d35d4a4fec889f1847a484cc45?cid=3babc6a11c1148728bac51aef1937f54", "track_number": 4, "type": "track", "uri": "spotify:track:6UweTkm7cVKfWIw6Sn1iU7", "release_date": "1993"}