{"artists": [{"external_urls": {"spotify": "https://open.spotify.com/artist/3crnzLy8R4lVwaigKEOz7V"}, "href": "https://api.spotify.com/v1/artists/3crnzLy8R4lVwaigKEOz7V", "id": "3crnzLy8R4lVwaigKEOz7V", "name": "E-40", "type": "artist", "uri": "spotify:artist:3crnzLy8R4lVwaigKEOz7V"}, {"external_urls": {"spotify": "https://open.spotify.com/artist/6nltEpEZtqZD1v4YJLlaZI"}, "href": "https://api.spotify.com/v1/artists/6nltEpEZtqZD1v4YJLlaZI", "id": "6nltEpEZtqZD1v4YJLlaZI", "name": "B-Legit", "type": "artist", "uri": "spotify:artist:6nltEpEZtqZD1v4YJLlaZI"}, {"external_urls": {"spotify": "https://open.spotify.com/artist/76iA4ibUsojQnLPscvrr9g"}, "href": "https://api.spotify.com/v1/artists/76iA4ibUsojQnLPscvrr9g", "id": "76iA4ibUsojQnLPscvrr9g", "name": "JT The 4th", "type": "artist", "uri": "spotify:artist:76iA4ibUsojQnLPscvrr9g"}], "available_markets": ["CA", "US"], "disc_number": 1, "duration_ms": 138018, "explicit": true, "external_urls": {"spotify": "https://open.spotify.com/track/5NzzQF3RX5nfeRRCtFLmGx"}, "href": "https://api.spotify.com/v1/tracks/5NzzQF3RX5nfeRRCtFLmGx", "id": "5NzzQF3RX5nfeRRCtFLmGx", "is_local": false, "name": "Fsho", "preview_url": null, "track_number": 10, "type": "track", "uri": "spotify:track:5NzzQF3RX5nfeRRCtFLmGx"}