{"artists": [{"external_urls": {"spotify": "https://open.spotify.com/artist/4AA474G2hRfrHyGrfyDseO"}, "href": "https://api.spotify.com/v1/artists/4AA474G2hRfrHyGrfyDseO", "id": "4AA474G2hRfrHyGrfyDseO", "name": "Mozzy", "type": "artist", "uri": "spotify:artist:4AA474G2hRfrHyGrfyDseO"}, {"external_urls": {"spotify": "https://open.spotify.com/artist/35cJT1IMCFHLeKiPcSpequ"}, "href": "https://api.spotify.com/v1/artists/35cJT1IMCFHLeKiPcSpequ", "id": "35cJT1IMCFHLeKiPcSpequ", "name": "DJ.Fresh", "type": "artist", "uri": "spotify:artist:35cJT1IMCFHLeKiPcSpequ"}, {"external_urls": {"spotify": "https://open.spotify.com/artist/4sBb9poDJRrHCZEVRkF2k0"}, "href": "https://api.spotify.com/v1/artists/4sBb9poDJRrHCZEVRkF2k0", "id": "4sBb9poDJRrHCZEVRkF2k0", "name": "Noble of the Outlawz", "type": "artist", "uri": "spotify:artist:4sBb9poDJRrHCZEVRkF2k0"}, {"external_urls": {"spotify": "https://open.spotify.com/artist/4TftIY06sTVxKdccj6tI9a"}, "href": "https://api.spotify.com/v1/artists/4TftIY06sTVxKdccj6tI9a", "id": "4TftIY06sTVxKdccj6tI9a", "name": "D Stax", "type": "artist", "uri": "spotify:artist:4TftIY06sTVxKdccj6tI9a"}], "available_markets": ["AD", "AE", "AG", "AL", "AM", "AO", "AR", "AT", "AU", "AZ", "BA", "BB", "BD", "BE", "BF", "BG", "BH", "BI", "BJ", "BN", "BO", "BR", "BS", "BT", "BW", "BY", "BZ", "CA", "CD", "CG", "CH", "CI", "CL", "CM", "CO", "CR", "CV", "CY", "CZ", "DE", "DJ", "DK", "DM", "DO", "DZ", "EC", "EE", "EG", "ES", "FI", "FJ", "FM", "FR", "GA", "GB", "GD", "GE", "GH", "GM", "GN", "GQ", "GR", "GT", "GW", "GY", "HK", "HN", "HR", "HT", "HU", "ID", "IE", "IL", "IN", "IQ", "IS", "IT", "JM", "JO", "JP", "KE", "KG", "KH", "KI", "KM", "KN", "KR", "KW", "KZ", "LA", "LB", "LC", "LI", "LK", "LR", "LS", "LT", "LU", "LV", "LY", "MA", "MC", "MD", "ME", "MG", "MH", "MK", "ML", "MN", "MO", "MR", "MT", "MU", "MV", "MW", "MX", "MY", "MZ", "NA", "NE", "NG", "NI", "NL", "NO", "NP", "NR", "NZ", "OM", "PA", "PE", "PG", "PH", "PK", "PL", "PS", "PT", "PW", "PY", "QA", "RO", "RS", "RW", "SA", "SB", "SC", "SE", "SG", "SI", "SK", "SL", "SM", "SN", "SR", "ST", "SV", "SZ", "TD", "TG", "TH", "TJ", "TL", "TN", "TO", "TR", "TT", "TV", "TW", "TZ", "UA", "UG", "US", "UY", "UZ", "VC", "VE", "VN", "VU", "WS", "XK", "ZA", "ZM", "ZW"], "disc_number": 1, "duration_ms": 228426, "explicit": true, "external_urls": {"spotify": "https://open.spotify.com/track/1QdDVfLP1jNAgml128DFL6"}, "href": "https://api.spotify.com/v1/tracks/1QdDVfLP1jNAgml128DFL6", "id": "1QdDVfLP1jNAgml128DFL6", "is_local": false, "name": "Curve Ball", "preview_url": "https://p.scdn.co/mp3-preview/27eea6043eff9291df14791ba02c0a83b3246052?cid=3babc6a11c1148728bac51aef1937f54", "track_number": 4, "type": "track", "uri": "spotify:track:1QdDVfLP1jNAgml128DFL6"}