{"artists": [{"external_urls": {"spotify": "https://open.spotify.com/artist/6I3M904Y9IwgDjrQ9pANiB"}, "href": "https://api.spotify.com/v1/artists/6I3M904Y9IwgDjrQ9pANiB", "id": "6I3M904Y9IwgDjrQ9pANiB", "name": "Kenny G", "type": "artist", "uri": "spotify:artist:6I3M904Y9IwgDjrQ9pANiB"}], "available_markets": ["AG", "AR", "AU", "BB", "BN", "BO", "BR", "BS", "BZ", "CL", "CO", "CR", "CW", "DM", "DO", "EC", "FJ", "GD", "GT", "GY", "HN", "HT", "JM", "JP", "KH", "KI", "KN", "KR", "LA", "LC", "MH", "MX", "MY", "NI", "NR", "NZ", "PA", "PE", "PG", "PW", "PY", "SB", "SR", "SV", "TH", "TO", "TT", "TV", "US", "UY", "VC", "VE", "VU", "WS"], "disc_number": 1, "duration_ms": 246333, "explicit": false, "external_urls": {"spotify": "https://open.spotify.com/track/3fXK7duAYNX832ASoLpzY7"}, "href": "https://api.spotify.com/v1/tracks/3fXK7duAYNX832ASoLpzY7", "id": "3fXK7duAYNX832ASoLpzY7", "is_local": false, "name": "One Man's Poison (Another Man's Sweetness)", "preview_url": "https://p.scdn.co/mp3-preview/12179fc2a68e518c81b75dc8f488339297f4112e?cid=3babc6a11c1148728bac51aef1937f54", "track_number": 2, "type": "track", "uri": "spotify:track:3fXK7duAYNX832ASoLpzY7", "release_date": "1985-07-01"}