{"artists": [{"external_urls": {"spotify": "https://open.spotify.com/artist/137W8MRPWKqSmrBGDBFSop"}, "href": "https://api.spotify.com/v1/artists/137W8MRPWKqSmrBGDBFSop", "id": "137W8MRPWKqSmrBGDBFSop", "name": "Wiz Khalifa", "type": "artist", "uri": "spotify:artist:137W8MRPWKqSmrBGDBFSop"}], "available_markets": ["AD", "AE", "AG", "AM", "AO", "AR", "AZ", "BB", "BD", "BE", "BF", "BH", "BI", "BJ", "BN", "BO", "BR", "BS", "BW", "BY", "BZ", "CA", "CD", "CG", "CI", "CL", "CM", "CO", "CR", "CV", "CW", "CY", "DJ", "DK", "DM", "DO", "DZ", "EC", "EG", "ES", "FI", "GA", "GD", "GE", "GH", "GM", "GN", "GQ", "GR", "GT", "GW", "HK", "HN", "HT", "ID", "IL", "IN", "IQ", "IS", "IT", "JM", "JO", "JP", "KE", "KG", "KH", "KM", "KN", "KR", "KW", "KZ", "LA", "LB", "LC", "LK", "LR", "LS", "LU", "LY", "MA", "MC", "MD", "MG", "ML", "MO", "MR", "MT", "MU", "MW", "MX", "MY", "MZ", "NA", "NE", "NG", "NI", "NL", "NO", "OM", "PA", "PE", "PH", "PK", "PT", "PY", "QA", "RW", "SA", "SC", "SE", "SG", "SL", "SM", "SN", "ST", "SV", "SZ", "TD", "TG", "TH", "TJ", "TL", "TN", "TR", "TT", "TW", "TZ", "UA", "UG", "US", "UY", "UZ", "VC", "VE", "VN", "ZA", "ZM", "ZW"], "disc_number": 1, "duration_ms": 259240, "explicit": true, "external_urls": {"spotify": "https://open.spotify.com/track/4X8SIs6X8At8ONaR405u8c"}, "href": "https://api.spotify.com/v1/tracks/4X8SIs6X8At8ONaR405u8c", "id": "4X8SIs6X8At8ONaR405u8c", "is_local": false, "name": "Mary 3x", "preview_url": "https://p.scdn.co/mp3-preview/373f782f52e5518e7cb8d17a99ecc000da79b160?cid=3babc6a11c1148728bac51aef1937f54", "track_number": 20, "type": "track", "uri": "spotify:track:4X8SIs6X8At8ONaR405u8c"}