{"artists": [{"external_urls": {"spotify": "https://open.spotify.com/artist/2nszamLjZFgu3Yx77mKxuC"}, "href": "https://api.spotify.com/v1/artists/2nszamLjZFgu3Yx77mKxuC", "id": "2nszamLjZFgu3Yx77mKxuC", "name": "UNKLE", "type": "artist", "uri": "spotify:artist:2nszamLjZFgu3Yx77mKxuC"}, {"external_urls": {"spotify": "https://open.spotify.com/artist/1fpXM23IoNckJ7NDAm8YJQ"}, "href": "https://api.spotify.com/v1/artists/1fpXM23IoNckJ7NDAm8YJQ", "id": "1fpXM23IoNckJ7NDAm8YJQ", "name": "Mark Lanegan", "type": "artist", "uri": "spotify:artist:1fpXM23IoNckJ7NDAm8YJQ"}, {"external_urls": {"spotify": "https://open.spotify.com/artist/6pBfwu2Yt96wWprf96vhpg"}, "href": "https://api.spotify.com/v1/artists/6pBfwu2Yt96wWprf96vhpg", "id": "6pBfwu2Yt96wWprf96vhpg", "name": "ESKA", "type": "artist", "uri": "spotify:artist:6pBfwu2Yt96wWprf96vhpg"}], "available_markets": ["AU", "NZ"], "disc_number": 1, "duration_ms": 354742, "explicit": false, "external_urls": {"spotify": "https://open.spotify.com/track/5Wooiamuz2xw1sTDjhF9hZ"}, "href": "https://api.spotify.com/v1/tracks/5Wooiamuz2xw1sTDjhF9hZ", "id": "5Wooiamuz2xw1sTDjhF9hZ", "is_local": false, "name": "Looking for the Rain", "preview_url": "https://p.scdn.co/mp3-preview/92668b12f8bccabc4590289e816fcfd4f1a1d8c2?cid=3babc6a11c1148728bac51aef1937f54", "track_number": 3, "type": "track", "uri": "spotify:track:5Wooiamuz2xw1sTDjhF9hZ"}