{"artists": [{"external_urls": {"spotify": "https://open.spotify.com/artist/1b1N51wmSK0ckxFAMPSSHO"}, "href": "https://api.spotify.com/v1/artists/1b1N51wmSK0ckxFAMPSSHO", "id": "1b1N51wmSK0ckxFAMPSSHO", "name": "The Impressions", "type": "artist", "uri": "spotify:artist:1b1N51wmSK0ckxFAMPSSHO"}, {"external_urls": {"spotify": "https://open.spotify.com/artist/2AV6XDIs32ofIJhkkDevjm"}, "href": "https://api.spotify.com/v1/artists/2AV6XDIs32ofIJhkkDevjm", "id": "2AV6XDIs32ofIJhkkDevjm", "name": "Curtis Mayfield", "type": "artist", "uri": "spotify:artist:2AV6XDIs32ofIJhkkDevjm"}], "available_markets": ["AT", "CH", "DE"], "disc_number": 1, "duration_ms": 201586, "explicit": false, "external_urls": {"spotify": "https://open.spotify.com/track/5Hjh6MZCwzM9AS81K1kemG"}, "href": "https://api.spotify.com/v1/tracks/5Hjh6MZCwzM9AS81K1kemG", "id": "5Hjh6MZCwzM9AS81K1kemG", "is_local": false, "name": "Sermonette", "preview_url": null, "track_number": 6, "type": "track", "uri": "spotify:track:5Hjh6MZCwzM9AS81K1kemG"}