{"artists": [{"external_urls": {"spotify": "https://open.spotify.com/artist/3Nrfpe0tUJi4K4DXYWgMUX"}, "href": "https://api.spotify.com/v1/artists/3Nrfpe0tUJi4K4DXYWgMUX", "id": "3Nrfpe0tUJi4K4DXYWgMUX", "name": "BTS", "type": "artist", "uri": "spotify:artist:3Nrfpe0tUJi4K4DXYWgMUX"}], "available_markets": ["KR"], "disc_number": 1, "duration_ms": 295127, "explicit": false, "external_urls": {"spotify": "https://open.spotify.com/track/17eyqbmGlFZHO9dW3sNeUb"}, "href": "https://api.spotify.com/v1/tracks/17eyqbmGlFZHO9dW3sNeUb", "id": "17eyqbmGlFZHO9dW3sNeUb", "is_local": false, "name": "Butterfly - Prologue Mix", "preview_url": "https://p.scdn.co/mp3-preview/8f2ae972f6272134257ebb9b0a58eff86ab3d389?cid=3babc6a11c1148728bac51aef1937f54", "track_number": 5, "type": "track", "uri": "spotify:track:17eyqbmGlFZHO9dW3sNeUb", "release_date": "2016-05-02"}