{"artists": [{"external_urls": {"spotify": "https://open.spotify.com/artist/7hJcb9fa4alzcOq3EaNPoG"}, "href": "https://api.spotify.com/v1/artists/7hJcb9fa4alzcOq3EaNPoG", "id": "7hJcb9fa4alzcOq3EaNPoG", "name": "Snoop Dogg", "type": "artist", "uri": "spotify:artist:7hJcb9fa4alzcOq3EaNPoG"}, {"external_urls": {"spotify": "https://open.spotify.com/artist/5NDMothbpdpq2xHqSjrrWn"}, "href": "https://api.spotify.com/v1/artists/5NDMothbpdpq2xHqSjrrWn", "id": "5NDMothbpdpq2xHqSjrrWn", "name": "Faith Evans", "type": "artist", "uri": "spotify:artist:5NDMothbpdpq2xHqSjrrWn"}, {"external_urls": {"spotify": "https://open.spotify.com/artist/74Ux2ec8OC0BiU4tB0ekCO"}, "href": "https://api.spotify.com/v1/artists/74Ux2ec8OC0BiU4tB0ekCO", "id": "74Ux2ec8OC0BiU4tB0ekCO", "name": "3rd Generation (Bereal Family)", "type": "artist", "uri": "spotify:artist:74Ux2ec8OC0BiU4tB0ekCO"}], "available_markets": ["AD", "AE", "AG", "AL", "AM", "AO", "AR", "AT", "AU", "AZ", "BA", "BB", "BD", "BE", "BF", "BG", "BH", "BI", "BJ", "BN", "BO", "BR", "BS", "BT", "BW", "BY", "BZ", "CA", "CD", "CG", "CH", "CI", "CL", "CM", "CO", "CR", "CV", "CY", "CZ", "DE", "DJ", "DK", "DM", "DO", "DZ", "EC", "EE", "EG", "ES", "FI", "FJ", "FM", "FR", "GA", "GB", "GD", "GE", "GH", "GM", "GN", "GQ", "GR", "GT", "GW", "GY", "HK", "HN", "HR", "HT", "HU", "ID", "IE", "IL", "IN", "IQ", "IS", "IT", "JM", "JO", "JP", "KE", "KG", "KH", "KI", "KM", "KN", "KR", "KW", "KZ", "LA", "LB", "LC", "LI", "LK", "LR", "LS", "LT", "LU", "LV", "LY", "MA", "MC", "MD", "ME", "MG", "MH", "MK", "ML", "MN", "MO", "MR", "MT", "MU", "MV", "MW", "MX", "MY", "MZ", "NA", "NE", "NG", "NI", "NL", "NO", "NP", "NR", "NZ", "OM", "PA", "PE", "PG", "PH", "PK", "PL", "PS", "PT", "PW", "PY", "QA", "RO", "RS", "RW", "SA", "SB", "SC", "SE", "SG", "SI", "SK", "SL", "SM", "SN", "SR", "ST", "SV", "SZ", "TD", "TG", "TH", "TJ", "TL", "TN", "TO", "TR", "TT", "TV", "TW", "TZ", "UA", "UG", "US", "UY", "UZ", "VC", "VE", "VN", "VU", "WS", "XK", "ZA", "ZM", "ZW"], "disc_number": 1, "duration_ms": 215493, "explicit": false, "external_urls": {"spotify": "https://open.spotify.com/track/1WPzLuZobA2iwQ8mcL7OoW"}, "href": "https://api.spotify.com/v1/tracks/1WPzLuZobA2iwQ8mcL7OoW", "id": "1WPzLuZobA2iwQ8mcL7OoW", "is_local": false, "name": "Saved (feat. Faith Evans & 3rd Generation (Bereal Family))", "preview_url": "https://p.scdn.co/mp3-preview/97a9abafe1f1ec92d1279d1574c64307d486bd6f?cid=3babc6a11c1148728bac51aef1937f54", "track_number": 7, "type": "track", "uri": "spotify:track:1WPzLuZobA2iwQ8mcL7OoW", "release_date": "2018-03-16"}