{"artists": [{"external_urls": {"spotify": "https://open.spotify.com/artist/0lEssBAxQl2In4RpaB1C2Y"}, "href": "https://api.spotify.com/v1/artists/0lEssBAxQl2In4RpaB1C2Y", "id": "0lEssBAxQl2In4RpaB1C2Y", "name": "Talib Kweli", "type": "artist", "uri": "spotify:artist:0lEssBAxQl2In4RpaB1C2Y"}, {"external_urls": {"spotify": "https://open.spotify.com/artist/0JecZKwHhhu33XL7HJKGpI"}, "href": "https://api.spotify.com/v1/artists/0JecZKwHhhu33XL7HJKGpI", "id": "0JecZKwHhhu33XL7HJKGpI", "name": "Kendra Ross", "type": "artist", "uri": "spotify:artist:0JecZKwHhhu33XL7HJKGpI"}], "available_markets": ["AE", "AG", "AM", "AO", "AR", "AU", "AZ", "BB", "BD", "BF", "BH", "BI", "BJ", "BN", "BO", "BR", "BS", "BT", "BW", "BZ", "CA", "CD", "CG", "CI", "CL", "CM", "CO", "CR", "CV", "DJ", "DM", "DO", "DZ", "EC", "EG", "FJ", "FM", "GA", "GD", "GE", "GH", "GM", "GN", "GQ", "GT", "GW", "GY", "HK", "HN", "HT", "ID", "IL", "IN", "IQ", "JM", "JO", "KE", "KG", "KH", "KI", "KM", "KN", "KR", "KW", "KZ", "LA", "LB", "LC", "LK", "LR", "LS", "LY", "MA", "MG", "MH", "ML", "MN", "MO", "MR", "MU", "MV", "MW", "MX", "MY", "MZ", "NA", "NE", "NG", "NI", "NP", "NR", "NZ", "OM", "PA", "PE", "PG", "PH", "PK", "PS", "PW", "PY", "QA", "RW", "SA", "SB", "SC", "SG", "SL", "SN", "SR", "ST", "SV", "SZ", "TD", "TG", "TH", "TJ", "TL", "TN", "TO", "TR", "TT", "TV", "TW", "TZ", "UG", "US", "UY", "UZ", "VC", "VE", "VN", "VU", "WS", "ZA", "ZM", "ZW"], "disc_number": 1, "duration_ms": 225720, "explicit": true, "external_urls": {"spotify": "https://open.spotify.com/track/4a55BIIuJ219eWHnfDisi5"}, "href": "https://api.spotify.com/v1/tracks/4a55BIIuJ219eWHnfDisi5", "id": "4a55BIIuJ219eWHnfDisi5", "is_local": false, "name": "I'm Waiting for You", "preview_url": "https://p.scdn.co/mp3-preview/1104a17bb4b13cec6dfc7f6e43604f881b3582c8?cid=3babc6a11c1148728bac51aef1937f54", "track_number": 7, "type": "track", "uri": "spotify:track:4a55BIIuJ219eWHnfDisi5", "release_date": "2011-01-25"}