{"artists": [{"external_urls": {"spotify": "https://open.spotify.com/artist/3Nrfpe0tUJi4K4DXYWgMUX"}, "href": "https://api.spotify.com/v1/artists/3Nrfpe0tUJi4K4DXYWgMUX", "id": "3Nrfpe0tUJi4K4DXYWgMUX", "name": "BTS", "type": "artist", "uri": "spotify:artist:3Nrfpe0tUJi4K4DXYWgMUX"}], "available_markets": ["KR"], "disc_number": 1, "duration_ms": 143862, "explicit": false, "external_urls": {"spotify": "https://open.spotify.com/track/7m932U1C6DsTBCC46EZpZj"}, "href": "https://api.spotify.com/v1/tracks/7m932U1C6DsTBCC46EZpZj", "id": "7m932U1C6DsTBCC46EZpZj", "is_local": false, "name": "Outro: Love Is Not Over", "preview_url": "https://p.scdn.co/mp3-preview/995ad687ae6fd8f8ce21c28fea3282e2594b1a17?cid=3babc6a11c1148728bac51aef1937f54", "track_number": 9, "type": "track", "uri": "spotify:track:7m932U1C6DsTBCC46EZpZj"}