{"artists": [{"external_urls": {"spotify": "https://open.spotify.com/artist/7hJcb9fa4alzcOq3EaNPoG"}, "href": "https://api.spotify.com/v1/artists/7hJcb9fa4alzcOq3EaNPoG", "id": "7hJcb9fa4alzcOq3EaNPoG", "name": "Snoop Dogg", "type": "artist", "uri": "spotify:artist:7hJcb9fa4alzcOq3EaNPoG"}, {"external_urls": {"spotify": "https://open.spotify.com/artist/2YZyLoL8N0Wb9xBt1NhZWg"}, "href": "https://api.spotify.com/v1/artists/2YZyLoL8N0Wb9xBt1NhZWg", "id": "2YZyLoL8N0Wb9xBt1NhZWg", "name": "Kendrick Lamar", "type": "artist", "uri": "spotify:artist:2YZyLoL8N0Wb9xBt1NhZWg"}, {"external_urls": {"spotify": "https://open.spotify.com/artist/1sBkRIssrMs1AbVkOJbc7a"}, "href": "https://api.spotify.com/v1/artists/1sBkRIssrMs1AbVkOJbc7a", "id": "1sBkRIssrMs1AbVkOJbc7a", "name": "Rick Ross", "type": "artist", "uri": "spotify:artist:1sBkRIssrMs1AbVkOJbc7a"}], "available_markets": ["GB"], "disc_number": 1, "duration_ms": 278146, "explicit": false, "external_urls": {"spotify": "https://open.spotify.com/track/3hxvLpkyVo3TXZEXDeebJx"}, "href": "https://api.spotify.com/v1/tracks/3hxvLpkyVo3TXZEXDeebJx", "id": "3hxvLpkyVo3TXZEXDeebJx", "is_local": false, "name": "I'm Ya Dogg (feat. Kendrick Lamar & Rick Ross)", "preview_url": "https://p.scdn.co/mp3-preview/d3780520a76aa4d949c3423d4f8d27a88ee1b20f?cid=3babc6a11c1148728bac51aef1937f54", "track_number": 10, "type": "track", "uri": "spotify:track:3hxvLpkyVo3TXZEXDeebJx"}