{"artists": [{"external_urls": {"spotify": "https://open.spotify.com/artist/6AVLthptCPhfrxlHadOBJD"}, "href": "https://api.spotify.com/v1/artists/6AVLthptCPhfrxlHadOBJD", "id": "6AVLthptCPhfrxlHadOBJD", "name": "Jill Scott", "type": "artist", "uri": "spotify:artist:6AVLthptCPhfrxlHadOBJD"}, {"external_urls": {"spotify": "https://open.spotify.com/artist/0Mz5XE0kb1GBnbLQm2VbcO"}, "href": "https://api.spotify.com/v1/artists/0Mz5XE0kb1GBnbLQm2VbcO", "id": "0Mz5XE0kb1GBnbLQm2VbcO", "name": "Mos Def", "type": "artist", "uri": "spotify:artist:0Mz5XE0kb1GBnbLQm2VbcO"}], "available_markets": ["CA", "US"], "disc_number": 1, "duration_ms": 305085, "explicit": false, "external_urls": {"spotify": "https://open.spotify.com/track/3z0isDhRJpZMCOc9Nq3G2v"}, "href": "https://api.spotify.com/v1/tracks/3z0isDhRJpZMCOc9Nq3G2v", "id": "3z0isDhRJpZMCOc9Nq3G2v", "is_local": false, "name": "Love Rain - Head Nod Mix / Remastered", "preview_url": null, "track_number": 19, "type": "track", "uri": "spotify:track:3z0isDhRJpZMCOc9Nq3G2v", "release_date": "2020-07-31"}