{"artists": [{"external_urls": {"spotify": "https://open.spotify.com/artist/13y7CgLHjMVRMDqxdx0Xdo"}, "href": "https://api.spotify.com/v1/artists/13y7CgLHjMVRMDqxdx0Xdo", "id": "13y7CgLHjMVRMDqxdx0Xdo", "name": "Gucci Mane", "type": "artist", "uri": "spotify:artist:13y7CgLHjMVRMDqxdx0Xdo"}, {"external_urls": {"spotify": "https://open.spotify.com/artist/31IZdHrCZ5pRhLz4zBxN3o"}, "href": "https://api.spotify.com/v1/artists/31IZdHrCZ5pRhLz4zBxN3o", "id": "31IZdHrCZ5pRhLz4zBxN3o", "name": "Riff Raff", "type": "artist", "uri": "spotify:artist:31IZdHrCZ5pRhLz4zBxN3o"}], "available_markets": ["IN"], "disc_number": 1, "duration_ms": 157093, "explicit": true, "external_urls": {"spotify": "https://open.spotify.com/track/6WctwHFnJrco1U9Poij6vP"}, "href": "https://api.spotify.com/v1/tracks/6WctwHFnJrco1U9Poij6vP", "id": "6WctwHFnJrco1U9Poij6vP", "is_local": false, "name": "I'm Too Much (feat. Riff Raff)", "preview_url": "https://p.scdn.co/mp3-preview/f94ee1f23908708e27b8a72c6d32fcc62d94125e?cid=3babc6a11c1148728bac51aef1937f54", "track_number": 10, "type": "track", "uri": "spotify:track:6WctwHFnJrco1U9Poij6vP", "release_date": "2015-06-16"}