{"artists": [{"external_urls": {"spotify": "https://open.spotify.com/artist/1lE6SEy8f84Zhjvp7r8yTD"}, "href": "https://api.spotify.com/v1/artists/1lE6SEy8f84Zhjvp7r8yTD", "id": "1lE6SEy8f84Zhjvp7r8yTD", "name": "Syleena Johnson", "type": "artist", "uri": "spotify:artist:1lE6SEy8f84Zhjvp7r8yTD"}], "available_markets": ["AT", "CH", "DE", "LI"], "disc_number": 1, "duration_ms": 281000, "explicit": false, "external_urls": {"spotify": "https://open.spotify.com/track/1bfplaRUonB86OJkayoQ9a"}, "href": "https://api.spotify.com/v1/tracks/1bfplaRUonB86OJkayoQ9a", "id": "1bfplaRUonB86OJkayoQ9a", "is_local": false, "name": "I'd Rather Be Wrong", "preview_url": "https://p.scdn.co/mp3-preview/c684885a93d924b531ebb5f4bf82c5619cff8fec?cid=3babc6a11c1148728bac51aef1937f54", "track_number": 14, "type": "track", "uri": "spotify:track:1bfplaRUonB86OJkayoQ9a", "release_date": "2001-07-12"}