{"artists": [{"external_urls": {"spotify": "https://open.spotify.com/artist/2nszamLjZFgu3Yx77mKxuC"}, "href": "https://api.spotify.com/v1/artists/2nszamLjZFgu3Yx77mKxuC", "id": "2nszamLjZFgu3Yx77mKxuC", "name": "UNKLE", "type": "artist", "uri": "spotify:artist:2nszamLjZFgu3Yx77mKxuC"}, {"external_urls": {"spotify": "https://open.spotify.com/artist/6GFfu1alUSrL7qazImC160"}, "href": "https://api.spotify.com/v1/artists/6GFfu1alUSrL7qazImC160", "id": "6GFfu1alUSrL7qazImC160", "name": "Keaton Henson", "type": "artist", "uri": "spotify:artist:6GFfu1alUSrL7qazImC160"}], "available_markets": ["AU", "NZ"], "disc_number": 1, "duration_ms": 314613, "explicit": false, "external_urls": {"spotify": "https://open.spotify.com/track/0bNxnDdW2eqoAmgaKu63Pb"}, "href": "https://api.spotify.com/v1/tracks/0bNxnDdW2eqoAmgaKu63Pb", "id": "0bNxnDdW2eqoAmgaKu63Pb", "is_local": false, "name": "Sonata", "preview_url": "https://p.scdn.co/mp3-preview/8e71085cb9ccc40f001d750ec0b5b60e1a9d32f6?cid=3babc6a11c1148728bac51aef1937f54", "track_number": 11, "type": "track", "uri": "spotify:track:0bNxnDdW2eqoAmgaKu63Pb"}