{"artists": [{"external_urls": {"spotify": "https://open.spotify.com/artist/49vCIUW46QY3L5vo1xVFoy"}, "href": "https://api.spotify.com/v1/artists/49vCIUW46QY3L5vo1xVFoy", "id": "49vCIUW46QY3L5vo1xVFoy", "name": "Trae Tha Truth", "type": "artist", "uri": "spotify:artist:49vCIUW46QY3L5vo1xVFoy"}], "available_markets": ["CA", "US"], "disc_number": 1, "duration_ms": 197013, "explicit": true, "external_urls": {"spotify": "https://open.spotify.com/track/0HlOUqNM4Um0jGi9iEbzpG"}, "href": "https://api.spotify.com/v1/tracks/0HlOUqNM4Um0jGi9iEbzpG", "id": "0HlOUqNM4Um0jGi9iEbzpG", "is_local": false, "name": "Life", "preview_url": "https://p.scdn.co/mp3-preview/0ccfe66ef4c891ccb0af0fd5c9882d5709af0caa?cid=3babc6a11c1148728bac51aef1937f54", "track_number": 8, "type": "track", "uri": "spotify:track:0HlOUqNM4Um0jGi9iEbzpG", "release_date": "2011-07-12"}