{"artists": [{"external_urls": {"spotify": "https://open.spotify.com/artist/6ohaQzKaXrobAL8paLSaxq"}, "href": "https://api.spotify.com/v1/artists/6ohaQzKaXrobAL8paLSaxq", "id": "6ohaQzKaXrobAL8paLSaxq", "name": "Salim\u2013Sulaiman", "type": "artist", "uri": "spotify:artist:6ohaQzKaXrobAL8paLSaxq"}, {"external_urls": {"spotify": "https://open.spotify.com/artist/1cw8NspBF8JctQm5rpn3pv"}, "href": "https://api.spotify.com/v1/artists/1cw8NspBF8JctQm5rpn3pv", "id": "1cw8NspBF8JctQm5rpn3pv", "name": "Rashid Khan", "type": "artist", "uri": "spotify:artist:1cw8NspBF8JctQm5rpn3pv"}], "available_markets": ["BD", "BT", "IN", "LK", "MV", "NP", "PK"], "disc_number": 1, "duration_ms": 336720, "explicit": false, "external_urls": {"spotify": "https://open.spotify.com/track/68xzxJGAD5oEboBynf2x8s"}, "href": "https://api.spotify.com/v1/tracks/68xzxJGAD5oEboBynf2x8s", "id": "68xzxJGAD5oEboBynf2x8s", "is_local": false, "name": "Cheene Re Mora Chain", "preview_url": "https://p.scdn.co/mp3-preview/b55bbbde2df2077645ccae37bb11347eb96e4d06?cid=3babc6a11c1148728bac51aef1937f54", "track_number": 6, "type": "track", "uri": "spotify:track:68xzxJGAD5oEboBynf2x8s", "release_date": "2013-09-07"}