{"artists": [{"external_urls": {"spotify": "https://open.spotify.com/artist/6l3HvQ5sa6mXTsMTB19rO5"}, "href": "https://api.spotify.com/v1/artists/6l3HvQ5sa6mXTsMTB19rO5", "id": "6l3HvQ5sa6mXTsMTB19rO5", "name": "J. Cole", "type": "artist", "uri": "spotify:artist:6l3HvQ5sa6mXTsMTB19rO5"}], "available_markets": ["AD", "AE", "AO", "AU", "BD", "BE", "BF", "BH", "BI", "BJ", "BN", "BT", "BW", "CD", "CG", "CI", "CM", "CV", "DE", "DJ", "DZ", "EG", "ES", "FJ", "FM", "FR", "GA", "GB", "GH", "GM", "GN", "GQ", "GW", "HK", "ID", "IE", "IL", "IN", "IQ", "IT", "JO", "JP", "KE", "KG", "KH", "KI", "KM", "KR", "KW", "LA", "LB", "LI", "LK", "LR", "LS", "LU", "LY", "MA", "MC", "MG", "MH", "ML", "MN", "MO", "MR", "MU", "MV", "MW", "MY", "MZ", "NA", "NE", "NG", "NP", "NR", "NZ", "OM", "PH", "PK", "PS", "PT", "PW", "QA", "RW", "SA", "SB", "SC", "SE", "SG", "SL", "SN", "ST", "SZ", "TD", "TG", "TH", "TJ", "TL", "TN", "TO", "TV", "TW", "TZ", "UG", "UZ", "VN", "VU", "WS", "ZA", "ZM", "ZW"], "disc_number": 1, "duration_ms": 235154, "explicit": true, "external_urls": {"spotify": "https://open.spotify.com/track/68Nw2xK5jKm3u9Szf4XB1Y"}, "href": "https://api.spotify.com/v1/tracks/68Nw2xK5jKm3u9Szf4XB1Y", "id": "68Nw2xK5jKm3u9Szf4XB1Y", "is_local": false, "name": "We On", "preview_url": "https://p.scdn.co/mp3-preview/ce0d84f222a82d267f6faa625da2ac0d53fc6c38?cid=3babc6a11c1148728bac51aef1937f54", "track_number": 11, "type": "track", "uri": "spotify:track:68Nw2xK5jKm3u9Szf4XB1Y", "release_date": "2014-11-09"}