{"artists": [{"external_urls": {"spotify": "https://open.spotify.com/artist/2hZ6jVi1cao5VlJHAEPzU7"}, "href": "https://api.spotify.com/v1/artists/2hZ6jVi1cao5VlJHAEPzU7", "id": "2hZ6jVi1cao5VlJHAEPzU7", "name": "GLC", "type": "artist", "uri": "spotify:artist:2hZ6jVi1cao5VlJHAEPzU7"}, {"external_urls": {"spotify": "https://open.spotify.com/artist/3L6bhGrHegoci41Jx2nP0V"}, "href": "https://api.spotify.com/v1/artists/3L6bhGrHegoci41Jx2nP0V", "id": "3L6bhGrHegoci41Jx2nP0V", "name": "Bump J", "type": "artist", "uri": "spotify:artist:3L6bhGrHegoci41Jx2nP0V"}], "available_markets": ["US"], "disc_number": 1, "duration_ms": 286026, "explicit": true, "external_urls": {"spotify": "https://open.spotify.com/track/5Ec1Ip2OZx7CvbmlCcNmct"}, "href": "https://api.spotify.com/v1/tracks/5Ec1Ip2OZx7CvbmlCcNmct", "id": "5Ec1Ip2OZx7CvbmlCcNmct", "is_local": false, "name": "The Big Knot - feat. Bump J; Explicit version", "preview_url": null, "track_number": 1, "type": "track", "uri": "spotify:track:5Ec1Ip2OZx7CvbmlCcNmct", "release_date": "2010-01-01"}