{"artists": [{"external_urls": {"spotify": "https://open.spotify.com/artist/4LEiUm1SRbFMgfqnQTwUbQ"}, "href": "https://api.spotify.com/v1/artists/4LEiUm1SRbFMgfqnQTwUbQ", "id": "4LEiUm1SRbFMgfqnQTwUbQ", "name": "Bon Iver", "type": "artist", "uri": "spotify:artist:4LEiUm1SRbFMgfqnQTwUbQ"}], "available_markets": ["AE", "AG", "AO", "AR", "AU", "BB", "BD", "BF", "BH", "BI", "BJ", "BN", "BO", "BR", "BS", "BT", "BW", "BZ", "CA", "CD", "CG", "CI", "CL", "CM", "CO", "CR", "CV", "DJ", "DM", "DO", "DZ", "EC", "EG", "FJ", "FM", "GA", "GD", "GH", "GM", "GN", "GQ", "GT", "GW", "GY", "HK", "HN", "HT", "ID", "IL", "IN", "IQ", "JM", "JO", "JP", "KE", "KG", "KH", "KI", "KM", "KN", "KR", "KW", "KZ", "LA", "LB", "LC", "LK", "LR", "LS", "LY", "MA", "MG", "MH", "ML", "MN", "MO", "MR", "MT", "MU", "MV", "MW", "MX", "MY", "MZ", "NA", "NE", "NG", "NI", "NP", "NR", "NZ", "OM", "PA", "PE", "PG", "PH", "PK", "PS", "PW", "PY", "QA", "RW", "SA", "SB", "SC", "SG", "SL", "SN", "SR", "ST", "SV", "SZ", "TD", "TG", "TH", "TJ", "TL", "TN", "TO", "TT", "TV", "TW", "TZ", "UG", "US", "UY", "UZ", "VC", "VE", "VN", "VU", "WS", "ZA", "ZM", "ZW"], "disc_number": 1, "duration_ms": 262079, "explicit": false, "external_urls": {"spotify": "https://open.spotify.com/track/5sYAPWzsEk8pd1OFhcQ67T"}, "href": "https://api.spotify.com/v1/tracks/5sYAPWzsEk8pd1OFhcQ67T", "id": "5sYAPWzsEk8pd1OFhcQ67T", "is_local": false, "name": "Perth", "preview_url": "https://p.scdn.co/mp3-preview/9bb304e9fa3e7e9d7273e6aa9d6ba15a04911ac0?cid=3babc6a11c1148728bac51aef1937f54", "track_number": 1, "type": "track", "uri": "spotify:track:5sYAPWzsEk8pd1OFhcQ67T", "release_date": "2011-06-21"}