{"artists": [{"external_urls": {"spotify": "https://open.spotify.com/artist/13y7CgLHjMVRMDqxdx0Xdo"}, "href": "https://api.spotify.com/v1/artists/13y7CgLHjMVRMDqxdx0Xdo", "id": "13y7CgLHjMVRMDqxdx0Xdo", "name": "Gucci Mane", "type": "artist", "uri": "spotify:artist:13y7CgLHjMVRMDqxdx0Xdo"}], "available_markets": ["IN"], "disc_number": 1, "duration_ms": 107023, "explicit": true, "external_urls": {"spotify": "https://open.spotify.com/track/3cSI67JpKG8GxML5PUoPTo"}, "href": "https://api.spotify.com/v1/tracks/3cSI67JpKG8GxML5PUoPTo", "id": "3cSI67JpKG8GxML5PUoPTo", "is_local": false, "name": "Worthy & Erving", "preview_url": "https://p.scdn.co/mp3-preview/d897443b214983c9d80557d4a50b8a4fdb302bc9?cid=3babc6a11c1148728bac51aef1937f54", "track_number": 26, "type": "track", "uri": "spotify:track:3cSI67JpKG8GxML5PUoPTo", "release_date": "2015-12-11"}