{"artists": [{"external_urls": {"spotify": "https://open.spotify.com/artist/01QTIT5P1pFP3QnnFSdsJf"}, "href": "https://api.spotify.com/v1/artists/01QTIT5P1pFP3QnnFSdsJf", "id": "01QTIT5P1pFP3QnnFSdsJf", "name": "Lupe Fiasco", "type": "artist", "uri": "spotify:artist:01QTIT5P1pFP3QnnFSdsJf"}], "available_markets": ["AO", "BF", "BI", "BJ", "BW", "CD", "CG", "CI", "CM", "CV", "DJ", "GA", "GH", "GM", "GN", "GQ", "GW", "KE", "KM", "LR", "LS", "MG", "ML", "MR", "MU", "MW", "MZ", "NA", "NE", "NG", "RW", "SC", "SL", "SN", "ST", "SZ", "TD", "TG", "TZ", "UG", "ZA", "ZM", "ZW"], "disc_number": 1, "duration_ms": 169346, "explicit": true, "external_urls": {"spotify": "https://open.spotify.com/track/23a5dvp7xHE00EuBD4PVwT"}, "href": "https://api.spotify.com/v1/tracks/23a5dvp7xHE00EuBD4PVwT", "id": "23a5dvp7xHE00EuBD4PVwT", "is_local": false, "name": "Dopamine Lit (Intro)", "preview_url": "https://p.scdn.co/mp3-preview/8d45bece596f0bd768749e179ec3a1ffe8cd3daa?cid=3babc6a11c1148728bac51aef1937f54", "track_number": 1, "type": "track", "uri": "spotify:track:23a5dvp7xHE00EuBD4PVwT"}