{"artists": [{"external_urls": {"spotify": "https://open.spotify.com/artist/13y7CgLHjMVRMDqxdx0Xdo"}, "href": "https://api.spotify.com/v1/artists/13y7CgLHjMVRMDqxdx0Xdo", "id": "13y7CgLHjMVRMDqxdx0Xdo", "name": "Gucci Mane", "type": "artist", "uri": "spotify:artist:13y7CgLHjMVRMDqxdx0Xdo"}], "available_markets": ["IN"], "disc_number": 1, "duration_ms": 158920, "explicit": true, "external_urls": {"spotify": "https://open.spotify.com/track/1U1YYeL7iNMaludAQ8SLGr"}, "href": "https://api.spotify.com/v1/tracks/1U1YYeL7iNMaludAQ8SLGr", "id": "1U1YYeL7iNMaludAQ8SLGr", "is_local": false, "name": "Coconut Ciroc", "preview_url": "https://p.scdn.co/mp3-preview/1c28733085b3028e0c7b29686993549e83b1550f?cid=3babc6a11c1148728bac51aef1937f54", "track_number": 11, "type": "track", "uri": "spotify:track:1U1YYeL7iNMaludAQ8SLGr", "release_date": "2015-06-09"}