{"artists": [{"external_urls": {"spotify": "https://open.spotify.com/artist/3crnzLy8R4lVwaigKEOz7V"}, "href": "https://api.spotify.com/v1/artists/3crnzLy8R4lVwaigKEOz7V", "id": "3crnzLy8R4lVwaigKEOz7V", "name": "E-40", "type": "artist", "uri": "spotify:artist:3crnzLy8R4lVwaigKEOz7V"}, {"external_urls": {"spotify": "https://open.spotify.com/artist/5lPsVvHVDr6R5mDxRUXdOs"}, "href": "https://api.spotify.com/v1/artists/5lPsVvHVDr6R5mDxRUXdOs", "id": "5lPsVvHVDr6R5mDxRUXdOs", "name": "A1", "type": "artist", "uri": "spotify:artist:5lPsVvHVDr6R5mDxRUXdOs"}], "available_markets": ["AE", "AM", "AO", "AZ", "BD", "BF", "BH", "BI", "BJ", "BN", "BT", "BW", "BY", "CD", "CG", "CI", "CM", "CV", "DJ", "EG", "GA", "GE", "GH", "GM", "GN", "GQ", "GW", "IN", "IQ", "JO", "KE", "KG", "KM", "KW", "KZ", "LB", "LK", "LR", "LS", "LY", "MD", "MG", "ML", "MN", "MR", "MU", "MV", "MW", "MY", "MZ", "NA", "NE", "NG", "NP", "OM", "PK", "PS", "QA", "RW", "SA", "SC", "SL", "SN", "ST", "SZ", "TD", "TG", "TJ", "TZ", "UA", "UG", "UZ", "ZA", "ZM", "ZW"], "disc_number": 1, "duration_ms": 309093, "explicit": false, "external_urls": {"spotify": "https://open.spotify.com/track/3cRM1LQtC7oZgXWuDTy9x0"}, "href": "https://api.spotify.com/v1/tracks/3cRM1LQtC7oZgXWuDTy9x0", "id": "3cRM1LQtC7oZgXWuDTy9x0", "is_local": false, "name": "Mayhem (feat. A-1)", "preview_url": "https://p.scdn.co/mp3-preview/2c2060d3e146488f165d9ee7eb4e00410b44c71c?cid=3babc6a11c1148728bac51aef1937f54", "track_number": 9, "type": "track", "uri": "spotify:track:3cRM1LQtC7oZgXWuDTy9x0", "release_date": "1994"}