{"external_urls": {"spotify": "https://open.spotify.com/artist/4cmA2QDPdzh8W2ytpyUGes"}, "followers": {"href": null, "total": 486656}, "genres": ["atl trap", "dirty south rap", "drill", "gangster rap", "houston rap", "pop rap", "rap", "southern hip hop", "trap"], "href": "https://api.spotify.com/v1/artists/4cmA2QDPdzh8W2ytpyUGes", "id": "4cmA2QDPdzh8W2ytpyUGes", "images": [{"height": 640, "url": "https://i.scdn.co/image/ab67616d0000b273a40ee6a0dd494f08a9dbe695", "width": 640}, {"height": 300, "url": "https://i.scdn.co/image/ab67616d00001e02a40ee6a0dd494f08a9dbe695", "width": 300}, {"height": 64, "url": "https://i.scdn.co/image/ab67616d00004851a40ee6a0dd494f08a9dbe695", "width": 64}], "name": "Young Scooter", "popularity": 59, "type": "artist", "uri": "spotify:artist:4cmA2QDPdzh8W2ytpyUGes"}