{"external_urls": {"spotify": "https://open.spotify.com/artist/6Z4JcgqrqgysyHIPRtDIHo"}, "followers": {"href": null, "total": 45438}, "genres": ["alternative r&b", "chill r&b", "indie r&b"], "href": "https://api.spotify.com/v1/artists/6Z4JcgqrqgysyHIPRtDIHo", "id": "6Z4JcgqrqgysyHIPRtDIHo", "images": [{"height": 640, "url": "https://i.scdn.co/image/ab6761610000e5ebbc29f9b76257133daa628010", "width": 640}, {"height": 320, "url": "https://i.scdn.co/image/ab67616100005174bc29f9b76257133daa628010", "width": 320}, {"height": 160, "url": "https://i.scdn.co/image/ab6761610000f178bc29f9b76257133daa628010", "width": 160}], "name": "Baby Rose", "popularity": 47, "type": "artist", "uri": "spotify:artist:6Z4JcgqrqgysyHIPRtDIHo"}