{"external_urls": {"spotify": "https://open.spotify.com/artist/4yTmEo2clwWq2jwelvqgVv"}, "followers": {"href": null, "total": 577526}, "genres": ["baton rouge rap", "pop rap", "southern hip hop", "trap"], "href": "https://api.spotify.com/v1/artists/4yTmEo2clwWq2jwelvqgVv", "id": "4yTmEo2clwWq2jwelvqgVv", "images": [{"height": 640, "url": "https://i.scdn.co/image/ab6761610000e5ebf740469a8164e49a178ff9a1", "width": 640}, {"height": 320, "url": "https://i.scdn.co/image/ab67616100005174f740469a8164e49a178ff9a1", "width": 320}, {"height": 160, "url": "https://i.scdn.co/image/ab6761610000f178f740469a8164e49a178ff9a1", "width": 160}], "name": "Fredo Bang", "popularity": 68, "type": "artist", "uri": "spotify:artist:4yTmEo2clwWq2jwelvqgVv"}