{"external_urls": {"spotify": "https://open.spotify.com/artist/6po19E0R9xffrgzrg84TC9"}, "followers": {"href": null, "total": 36464}, "genres": ["atl hip hop", "indie hip hop", "trap soul", "underground hip hop"], "href": "https://api.spotify.com/v1/artists/6po19E0R9xffrgzrg84TC9", "id": "6po19E0R9xffrgzrg84TC9", "images": [{"height": 640, "url": "https://i.scdn.co/image/ab6761610000e5eb11b8a0652a709c974434e398", "width": 640}, {"height": 320, "url": "https://i.scdn.co/image/ab6761610000517411b8a0652a709c974434e398", "width": 320}, {"height": 160, "url": "https://i.scdn.co/image/ab6761610000f17811b8a0652a709c974434e398", "width": 160}], "name": "Quentin Miller", "popularity": 49, "type": "artist", "uri": "spotify:artist:6po19E0R9xffrgzrg84TC9"}