{"external_urls": {"spotify": "https://open.spotify.com/artist/2x6jz70u3sZq75tW10akUW"}, "followers": {"href": null, "total": 151092}, "genres": ["alternative hip hop", "boom bap", "hardcore hip hop", "hip hop", "turntablism", "underground rap"], "href": "https://api.spotify.com/v1/artists/2x6jz70u3sZq75tW10akUW", "id": "2x6jz70u3sZq75tW10akUW", "images": [{"height": 640, "url": "https://i.scdn.co/image/ab6761610000e5ebcce72dbf9ccf498849346883", "width": 640}, {"height": 320, "url": "https://i.scdn.co/image/ab67616100005174cce72dbf9ccf498849346883", "width": 320}, {"height": 160, "url": "https://i.scdn.co/image/ab6761610000f178cce72dbf9ccf498849346883", "width": 160}], "name": "Sean Price", "popularity": 52, "type": "artist", "uri": "spotify:artist:2x6jz70u3sZq75tW10akUW"}