{"external_urls": {"spotify": "https://open.spotify.com/artist/6QxfNzuPwvVnH5n1U24Cmh"}, "followers": {"href": null, "total": 49688}, "genres": ["classic italian pop", "musica lombarda"], "href": "https://api.spotify.com/v1/artists/6QxfNzuPwvVnH5n1U24Cmh", "id": "6QxfNzuPwvVnH5n1U24Cmh", "images": [{"height": 640, "url": "https://i.scdn.co/image/ab67616d0000b2734b13c451bc637b16572e9fa5", "width": 640}, {"height": 300, "url": "https://i.scdn.co/image/ab67616d00001e024b13c451bc637b16572e9fa5", "width": 300}, {"height": 64, "url": "https://i.scdn.co/image/ab67616d000048514b13c451bc637b16572e9fa5", "width": 64}], "name": "Gigliola Cinquetti", "popularity": 48, "type": "artist", "uri": "spotify:artist:6QxfNzuPwvVnH5n1U24Cmh"}