{"external_urls": {"spotify": "https://open.spotify.com/artist/4EYRKWX3RvHihDHDr8TocR"}, "followers": {"href": null, "total": 24167}, "genres": ["instrumental soul", "memphis soul", "soul", "southern soul"], "href": "https://api.spotify.com/v1/artists/4EYRKWX3RvHihDHDr8TocR", "id": "4EYRKWX3RvHihDHDr8TocR", "images": [{"height": 640, "url": "https://i.scdn.co/image/ab67616d0000b27344e5f4c58dbecf728edd50fe", "width": 640}, {"height": 300, "url": "https://i.scdn.co/image/ab67616d00001e0244e5f4c58dbecf728edd50fe", "width": 300}, {"height": 64, "url": "https://i.scdn.co/image/ab67616d0000485144e5f4c58dbecf728edd50fe", "width": 64}], "name": "The Mar-Keys", "popularity": 37, "type": "artist", "uri": "spotify:artist:4EYRKWX3RvHihDHDr8TocR"}