{"external_urls": {"spotify": "https://open.spotify.com/artist/2wIVse2owClT7go1WT98tk"}, "followers": {"href": null, "total": 1940863}, "genres": ["dance pop", "hip hop", "hip pop", "pop", "pop rap", "r&b", "rap", "urban contemporary", "virginia hip hop"], "href": "https://api.spotify.com/v1/artists/2wIVse2owClT7go1WT98tk", "id": "2wIVse2owClT7go1WT98tk", "images": [{"height": 640, "url": "https://i.scdn.co/image/ab6761610000e5ebf6691f40d906f097e9fbaa4c", "width": 640}, {"height": 320, "url": "https://i.scdn.co/image/ab67616100005174f6691f40d906f097e9fbaa4c", "width": 320}, {"height": 160, "url": "https://i.scdn.co/image/ab6761610000f178f6691f40d906f097e9fbaa4c", "width": 160}], "name": "Missy Elliott", "popularity": 75, "type": "artist", "uri": "spotify:artist:2wIVse2owClT7go1WT98tk"}